abstractgateway/__init__.py
abstractgateway/app.py
abstractgateway/cli.py
abstractgateway/config.py
abstractgateway/runner.py
abstractgateway/service.py
abstractgateway/stores.py
abstractgateway/hosts/__init__.py
abstractgateway/hosts/bundle_host.py
abstractgateway/hosts/visualflow_host.py
abstractgateway/routes/__init__.py
abstractgateway/routes/gateway.py
abstractgateway/security/__init__.py
abstractgateway/security/gateway_security.py
abstractgateway-0.1.0.dist-info/METADATA
abstractgateway-0.1.0.dist-info/WHEEL
abstractgateway-0.1.0.dist-info/entry_points.txt
abstractgateway-0.1.0.dist-info/RECORD
