Metadata-Version: 2.4
Name: abstractgateway
Version: 0.1.0
Summary: AbstractGateway: deployable Run Gateway host for AbstractRuntime (commands + ledger).
Project-URL: GitHub, https://github.com/lpalbou/abstractgateway
Author: Laurent-Philippe Albou
License: MIT
Requires-Python: >=3.10
Requires-Dist: abstractruntime>=0.4.0
Requires-Dist: fastapi>=0.100.0
Requires-Dist: uvicorn[standard]>=0.23.0
Provides-Extra: dev
Requires-Dist: httpx>=0.27.0; extra == 'dev'
Requires-Dist: pytest>=7.0.0; extra == 'dev'
Provides-Extra: visualflow
Requires-Dist: abstractflow>=0.3.0; extra == 'visualflow'
